SimpleEva/EVAController.py
SimpleEva/Example.py
SimpleEva/__innit__.py
SimpleEva-0.0.2.dist-info/METADATA
SimpleEva-0.0.2.dist-info/WHEEL
SimpleEva-0.0.2.dist-info/top_level.txt
SimpleEva-0.0.2.dist-info/RECORD
