Metadata-Version: 2.1
Name: SimpleEva
Version: 0.0.2
Summary: A simple library for controlling Eva
Author: Tom Brothers
License: BSD
Keywords: EVA robot arm
Classifier: Development Status :: 3 - Alpha
Classifier: Topic :: Utilities
Classifier: License :: OSI Approved :: BSD License
Requires-Dist: evasdk
